odoo/addons/account_analytic_distribution_manual_date/README.rst
odoo/addons/account_analytic_distribution_manual_date/__init__.py
odoo/addons/account_analytic_distribution_manual_date/__manifest__.py
odoo/addons/account_analytic_distribution_manual_date/i18n/account_analytic_distribution_manual_date.pot
odoo/addons/account_analytic_distribution_manual_date/i18n/ca.po
odoo/addons/account_analytic_distribution_manual_date/i18n/es .po
odoo/addons/account_analytic_distribution_manual_date/i18n/it.po
odoo/addons/account_analytic_distribution_manual_date/models/__init__.py
odoo/addons/account_analytic_distribution_manual_date/models/account_analytic_distribution_manual.py
odoo/addons/account_analytic_distribution_manual_date/models/account_move.py
odoo/addons/account_analytic_distribution_manual_date/readme/CONTRIBUTORS.md
odoo/addons/account_analytic_distribution_manual_date/readme/DESCRIPTION.md
odoo/addons/account_analytic_distribution_manual_date/readme/USAGE.md
odoo/addons/account_analytic_distribution_manual_date/static/description/icon.png
odoo/addons/account_analytic_distribution_manual_date/static/description/index.html
odoo/addons/account_analytic_distribution_manual_date/static/src/components/analytic_distribution/analytic_distribution.esm.js
odoo/addons/account_analytic_distribution_manual_date/tests/__init__.py
odoo/addons/account_analytic_distribution_manual_date/tests/test_manual_distribution_date.py
odoo/addons/account_analytic_distribution_manual_date/views/account_analytic_distribution_manual_views.xml
odoo_addon_account_analytic_distribution_manual_date-17.0.1.0.0.4.dist-info/METADATA
odoo_addon_account_analytic_distribution_manual_date-17.0.1.0.0.4.dist-info/WHEEL
odoo_addon_account_analytic_distribution_manual_date-17.0.1.0.0.4.dist-info/top_level.txt
odoo_addon_account_analytic_distribution_manual_date-17.0.1.0.0.4.dist-info/RECORD
